decoder_3-to-8/decoder_3-to-8.v
// 3-to-8 Line Decoder
// 8 AND Gates on the output.
// 1 x 2-to-4 Line Decoder and 1 x 1-to-2 Line Decoder.
module decoder3to8(A, D);

input [2:0] A;
output [7:0] D;

wire [5:0] W;

decoder2to4 u0(.A(A[1:0]), .D(W[3:0]));
decoder1to2 u1(.A(A[2]), .D(W[5:4]));

assign D[7] = W[5] & W[3]; 
assign D[6] = W[5] & W[2]; 
assign D[5] = W[5] & W[1]; 
assign D[4] = W[5] & W[0]; 
assign D[3] = W[4] & W[3];
assign D[2] = W[4] & W[2];  
assign D[1] = W[4] & W[1]; 
assign D[0] = W[4] & W[0]; 
endmodule

module decoder2to4(A,D);

input [1:0] A;
output [3:0] D;

wire [3:0] W;

decoder1to2 U0(.A(A[0]), .D(W[1:0]));
decoder1to2 U1(.A(A[1]), .D(W[3:2]));

assign D[3] = W[3] & W[1];
assign D[2] = W[3] & W[0];
assign D[1] = W[2] & W[1];
assign D[0] = W[2] & W[0];


endmodule

module decoder1to2(A,D);

input A;
output[1:0] D;

assign D[1] = A;
assign D[0] = ~A;


endmodule

decoder_3-to-8_tb.v
`timescale  1ns/1ns
`include "decoder_3-to-8.v"

module decoder3to8_tb;

reg  [2:0] A;
wire [7:0] D;

decoder3to8 UUT(A, D);

initial begin
    $dumpfile("decoder_3-to-8.vcd");
    $dumpvars(0, decoder3to8_tb);
   
    A = 3'b111; #20;
    A = 3'b110; #20;
    A = 3'b101; #20;
    A = 3'b100; #20;
    A = 3'b011; #20;
    A = 3'b010; #20;
    A = 3'b001; #20;
    A = 3'b000; #20;
   
end

endmodule

decoder_3-to-8.vcd
$date
	Fri May 07 11:26:48 2021
$end
$version
	Icarus Verilog
$end
$timescale
	1ns
$end
$scope module decoder3to8_tb $end
$var wire 8 ! D [7:0] $end
$var reg 3 " A [2:0] $end
$scope module UUT $end
$var wire 3 # A [2:0] $end
$var wire 6 $ W [5:0] $end
$var wire 8 % D [7:0] $end
$scope module u0 $end
$var wire 2 & A [1:0] $end
$var wire 4 ' W [3:0] $end
$var wire 4 ( D [3:0] $end
$scope module U0 $end
$var wire 1 ) A $end
$var wire 2 * D [1:0] $end
$upscope $end
$scope module U1 $end
$var wire 1 + A $end
$var wire 2 , D [1:0] $end
$upscope $end
$upscope $end
$scope module u1 $end
$var wire 1 - A $end
$var wire 2 . D [1:0] $end
$upscope $end
$upscope $end
$upscope $end
$enddefinitions $end
#0
$dumpvars
b10 .
1-
b10 ,
1+
b10 *
1)
b1000 (
b1010 '
b11 &
b10000000 %
b101000 $
b111 #
b111 "
b10000000 !
$end
#20
b1000000 !
b1000000 %
b100100 $
b100 (
b1001 '
b1 *
0)
b10 &
b110 "
b110 #
#40
b100000 !
b100000 %
b100010 $
b10 (
b10 *
1)
b110 '
b1 ,
0+
b1 &
b101 "
b101 #
#60
b10000 !
b10000 %
b100001 $
b1 (
b101 '
b1 *
0)
b0 &
b100 "
b100 #
#80
b1000 (
b1000 !
b1000 %
b10 *
1)
b1010 '
b10 ,
1+
b11 &
b11000 $
b1 .
0-
b11 "
b11 #
#100
b100 !
b100 %
b10100 $
b100 (
b1001 '
b1 *
0)
b10 &
b10 "
b10 #
#120
b10 !
b10 %
b10010 $
b10 (
b10 *
1)
b110 '
b1 ,
0+
b1 &
b1 "
b1 #
#140
b1 !
b1 %
b10001 $
b1 (
b101 '
b1 *
0)
b0 &
b0 "
b0 #
